{
  "type": "minecraft:gift",
  "pools": [
    {
      "rolls": 1,
      "entries": [
        {
          "type": "minecraft:item",
          "name": "ftbquests:book"
        }
      ]
    },
    {
      "rolls": 1,
      "entries": [
        {
          "type": "minecraft:item",
          "name": "minecraft:wooden_sword"
        }
      ]
    },
    {
      "rolls": 1,
      "entries": [
        {
          "type": "minecraft:item",
          "name": "farmersdelight:chicken_sandwich",
          "functions": [
            {
              "function": "minecraft:set_count",
              "count": 5
            }
          ]
        }
      ]
    },
    {
      "rolls": 1,
      "entries": [
        {
          "type": "minecraft:item",
          "name": "minecraft:torch",
          "functions": [
            {
              "function": "minecraft:set_count",
              "count": 10
            }
          ]
        }
      ]
    }
  ],
  "random_sequence": "treasurebags:bags/spawn"
}