{"stats":{"minecraft:used":{"minecraft:stone_shovel":7,"minecraft:stone_pickaxe":322,"minecraft:oak_planks":6,"minecraft:shield":2,"minecraft:chest":2,"minecraft:wooden_pickaxe":5,"minecraft:iron_chestplate":1,"minecraft:torch":44,"minecraft:dirt":5,"minecraft:crafting_table":10,"minecraft:blast_furnace":1,"minecraft:white_bed":1,"waystones:waystone":1,"minecraft:wooden_axe":7,"minecraft:diamond_pickaxe":9,"minecraft:iron_axe":8,"minecraft:bread":15,"minecraft:iron_pickaxe":256,"minecraft:iron_helmet":1,"minecraft:stone_axe":51,"minecraft:cobblestone":110,"minecraft:furnace":3,"minecraft:andesite":2,"alexsmobs:animal_dictionary":2,"minecraft:egg":1,"minecraft:cooked_beef":4},"minecraft:crafted":{"minecraft:oak_planks":52,"minecraft:stone_shovel":1,"minecraft:crafting_table":5,"minecraft:spruce_planks":24,"minecraft:iron_helmet":1,"minecraft:wooden_pickaxe":1,"minecraft:furnace":2,"minecraft:birch_planks":24,"minecraft:stone_axe":1,"minecraft:air":0,"minecraft:diamond_pickaxe":1,"minecraft:iron_chestplate":1,"minecraft:shield":1,"minecraft:iron_axe":1,"minecraft:stick":40,"minecraft:iron_ingot":23,"minecraft:iron_pickaxe":2,"minecraft:stone_pickaxe":3,"minecraft:wooden_axe":1,"minecraft:chest":2,"minecraft:iron_leggings":1,"minecraft:white_bed":1,"minecraft:torch":52},"minecraft:mined":{"minecraft:tuff":1,"minecraft:spruce_planks":1,"iceandfire:silver_ore":3,"minecraft:deepslate_diamond_ore":8,"minecraft:crafting_table":5,"minecraft:torch":5,"minecraft:blast_furnace":2,"minecraft:grass_block":7,"minecraft:tall_grass":12,"minecraft:copper_ore":4,"minecraft:cobblestone":14,"minecraft:oak_planks":4,"minecraft:wall_torch":6,"alexscaves:cake_layer":10,"minecraft:large_fern":1,"minecraft:furnace":1,"evilcraft:dark_ore_deepslate":2,"minecraft:birch_log":6,"minecraft:iron_ore":22,"minecraft:sweet_berry_bush":2,"minecraft:andesite":154,"minecraft:birch_leaves":8,"minecraft:stripped_spruce_log":1,"evilcraft:dark_ore":4,"minecraft:grass":6,"minecraft:oak_log":13,"minecraft:coal_ore":62,"minecraft:gravel":2,"minecraft:dirt":12,"minecraft:stripped_oak_log":3,"alexscaves:block_of_chocolate":9,"minecraft:stone":236,"minecraft:oak_leaves":4,"minecraft:deepslate":56},"minecraft:custom":{"minecraft:interact_with_furnace":13,"lootr:looted_stat":18,"minecraft:mob_kills":14,"minecraft:interact_with_crafting_table":25,"minecraft:interact_with_loom":4,"minecraft:interact_with_campfire":4,"minecraft:leave_game":1,"minecraft:time_since_death":52467,"minecraft:sleep_in_bed":4,"minecraft:time_since_rest":35829,"minecraft:waystone_activated":2,"minecraft:sprint_one_cm":199077,"minecraft:damage_taken":1521,"minecraft:walk_one_cm":96010,"minecraft:damage_blocked_by_shield":90,"minecraft:drop":22,"minecraft:damage_dealt":1541,"minecraft:swim_one_cm":5496,"minecraft:talked_to_villager":1,"minecraft:fly_one_cm":413653,"minecraft:open_chest":2,"minecraft:crouch_one_cm":31836,"minecraft:play_time":90611,"minecraft:deaths":3,"minecraft:sneak_time":15707,"minecraft:walk_under_water_one_cm":2101,"minecraft:jump":2058,"minecraft:interact_with_blast_furnace":3,"minecraft:walk_on_water_one_cm":6699,"minecraft:total_world_time":90611,"minecraft:fall_one_cm":72857},"minecraft:broken":{"minecraft:stone_pickaxe":1,"minecraft:iron_pickaxe":1},"minecraft:killed":{"minecraft:pig":2,"minecraft:spider":2,"minecraft:creeper":1,"minecraft:sheep":4,"minecraft:cow":5},"minecraft:dropped":{"minecraft:wheat_seeds":3,"alexsmobs:animal_dictionary":1,"farmersdelight:cabbage_seeds":3,"minecraft:oak_planks":23,"minecraft:stripped_oak_log":3,"evilcraft:flesh_humanoid":1,"minecraft:torch":16,"minecraft:wooden_axe":1,"minecraft:andesite":9,"minecraft:wooden_pickaxe":1,"minecraft:stone_pickaxe":3,"alexscaves:cake_layer":9,"iceandfire:manuscript":15},"minecraft:killed_by":{"minecraft:player":1,"iceandfire:ice_dragon":2},"minecraft:picked_up":{"minecraft:stripped_oak_log":3,"minecraft:birch_log":6,"minecraft:crafting_table":5,"alexscaves:cake_layer":9,"minecraft:cooked_beef":4,"minecraft:glow_ink_sac":18,"minecraft:andesite":151,"minecraft:leather":9,"minecraft:tuff":1,"minecraft:oak_log":13,"evilcraft:flesh_humanoid":1,"minecraft:dirt":19,"minecraft:string":1,"minecraft:raw_copper":11,"minecraft:wheat_seeds":3,"minecraft:cobbled_deepslate":56,"minecraft:stone_pickaxe":1,"minecraft:beef":9,"minecraft:oak_planks":2,"minecraft:egg":1,"minecraft:furnace":1,"minecraft:raw_iron":20,"minecraft:sweet_berries":7,"minecraft:torch":12,"minecraft:gravel":2,"minecraft:porkchop":4,"minecraft:blast_furnace":2,"minecraft:spider_eye":1,"minecraft:arrow":2,"minecraft:diamond":8,"waystones:waystone":1,"evilcraft:dark_gem":27,"alexscaves:block_of_chocolate":9,"minecraft:mutton":5,"iceandfire:silver_nugget":22,"minecraft:coal":75,"minecraft:white_wool":4,"iceandfire:raw_silver":3,"minecraft:cobblestone":248}},"DataVersion":3465}