{
    "type": "apotheosis:salvaging",
    "input": [
        {
            "item": "minecraft:chainmail_helmet"
        },
        {
            "item": "minecraft:chainmail_chestplate"
        },
        {
            "item": "minecraft:chainmail_leggings"
        },
        {
            "item": "minecraft:chainmail_boots"
        }
    ],
    "outputs": [
        {
            "max_count": 3,
            "min_count": 1,
            "stack": {
                "count": 1,
                "id": "minecraft:chain"
            }
        }
    ]
}